{
    "#hash_210a8489": [
        {
            "entryname": "scriptbundle&default_zombies_realm_3",
            "hash_a949845f": 12,
            "hash_857deb66": 100
        },
        {
            "entryname": "scriptbundle&survival_ai_dog_molotov",
            "hash_a949845f": 5,
            "hash_857deb66": 30
        },
        {
            "entryname": "scriptbundle&survival_ai_raz",
            "hash_a949845f": 2,
            "hash_857deb66": 30
        },
        {
            "entryname": "scriptbundle&inf_elites",
            "hash_a949845f": 1,
            "hash_857deb66": 30
        }
    ],
    "hash_d961aeb3": 0.22,
    "configstringfiletype": "scriptbundle",
    "type": "survivalailist",
    "name": "portal_drop_ambush_realm_3_variant_3"
}