{
    "description": "localized19#hash_742803a6e3b86f85",
    "itemspawnentry": "scriptbundle#item_zmintel_survival_maxis_document_2",
    "configstringfiletype": "scriptbundle",
    "hash_7b26d0bb": "#enemy_drop",
    "hash_4138e7ed": 0,
    "model": "model#hash_2d4c54d31e26fd",
    "hash_824079e7": "#survival",
    "uimodel": "model#hash_33e2fc0d3cea4e1a",
    "hash_2a12d36": 0,
    "type": "zmintel",
    "season": 2,
    "hash_ad4ad686": "#maxis",
    "hash_217aec15": "localized19#hash_504b8aedbf9a040a",
    "name": "zmintel_survival_maxis_document_2",
    "hash_9be0526e": "#document",
    "hash_83e219de": "#release_initial",
    "hash_53be913a": 5,
    "title": "localized19#hash_f3bc26d022047d3",
    "hash_4efbbcfe": 0
}