{
    "description": "localized19#hash_1d19228c46be5dcc",
    "configstringfiletype": "scriptbundle",
    "hash_7b26d0bb": "#enemy_drop",
    "hash_4138e7ed": 0,
    "hash_824079e7": "#survival",
    "uimodel": "model#hash_15bdaf1e1c51893b",
    "hash_2a12d36": 0,
    "type": "zmintel",
    "season": 2,
    "hash_ad4ad686": "#dark_aether",
    "hash_217aec15": "localized19#hash_375392711cfadc5b",
    "name": "zmintel_survival_darkaether_document_3",
    "hash_9be0526e": "#document",
    "hash_83e219de": "#release_initial",
    "hash_53be913a": 5,
    "title": "localized19#hash_615d7759906b1b64",
    "hash_4efbbcfe": 0,
    "hash_6073bf8f": "model#hash_3f08210f15fb0a46"
}