{
    "var_572513bb": [
        {
            "season": "#hash_2c11594a466148ad",
            "var_cb9cd317": "#zmintel_tungsten_omega_audiolog_1"
        },
        {
            "season": "#hash_2c11594a466148ad",
            "var_cb9cd317": "#zmintel_tungsten_omega_audiolog_2"
        },
        {
            "season": "#hash_2c11594a466148ad",
            "var_cb9cd317": "#zmintel_tungsten_omega_audiolog_3"
        },
        {
            "season": "#hash_2c11594a466148ad",
            "var_cb9cd317": "#zmintel_tungsten_omega_audiolog_4"
        },
        {
            "season": "#hash_2c11594a466148ad",
            "var_cb9cd317": "#zmintel_tungsten_omega_document_1"
        },
        {
            "season": "#hash_2c11594a466148ad",
            "var_cb9cd317": "#zmintel_tungsten_omega_document_2"
        },
        {
            "season": "#hash_2c11594a466148ad",
            "var_cb9cd317": "#zmintel_tungsten_omega_document_3"
        },
        {
            "season": "#hash_2c11594a466148ad",
            "var_cb9cd317": "#zmintel_tungsten_omega_document_4"
        },
        {
            "season": "#hash_2c11594a466148ad",
            "var_cb9cd317": "#zmintel_tungsten_omega_document_5"
        },
        {
            "season": "#hash_2c11594a466148ad",
            "var_cb9cd317": "#zmintel_tungsten_omega_document_6"
        },
        {
            "season": "#hash_2c11594a466148ad",
            "var_cb9cd317": "#zmintel_tungsten_omega_document_7"
        },
        {
            "season": "#hash_2c11594a466148ad",
            "var_cb9cd317": "#zmintel_tungsten_omega_document_8"
        },
        {
            "season": "#hash_2c11594a466148ad",
            "var_cb9cd317": "#zmintel_tungsten_omega_document_9"
        }
    ],
    "var_922067c4": "scriptbundle",
    "type": "zmintel_list",
    "name": "zmintel_list_zm_tungsten_omega_intel_all"
}