{
    "#hash_df2d0a90": [
        {
            "hash_4cae1b36": 0,
            "hash_fce3a1c3": 0,
            "HideCursor": 0,
            "hash_e2b21dfe": 0,
            "hash_dabbb2e7": "uin_cp_screentext_auto_main",
            "hash_f49bdf40": "localized19#hash_171d750b451b3ace",
            "DrawByLineScreenMax": 0,
            "ShowNewLineMarker": 1,
            "RemoveCursorOnComplete": 1,
            "FlashHighlight": 0,
            "MaskText": 0,
            "DrawByLine": 0
        },
        {
            "hash_4cae1b36": 0,
            "hash_fce3a1c3": 0,
            "HideCursor": 0,
            "hash_e2b21dfe": 1,
            "hash_dabbb2e7": "uin_cp_screentext_auto_main",
            "hash_f49bdf40": "localized19#hash_171d740b451b391b",
            "DrawByLineScreenMax": 0,
            "ShowNewLineMarker": 0,
            "RemoveCursorOnComplete": 1,
            "FlashHighlight": 0,
            "MaskText": 0,
            "DrawByLine": 0
        },
        {
            "hash_4cae1b36": 0,
            "hash_fce3a1c3": 0,
            "HideCursor": 1,
            "hash_e2b21dfe": 1,
            "hash_dabbb2e7": "uin_cp_screentext_auto_main",
            "hash_f49bdf40": "localized19#hash_171d730b451b3768",
            "DrawByLineScreenMax": 0,
            "ShowNewLineMarker": 0,
            "RemoveCursorOnComplete": 1,
            "FlashHighlight": 0,
            "MaskText": 0,
            "DrawByLine": 1
        },
        {
            "hash_4cae1b36": 0,
            "hash_fce3a1c3": 0,
            "HideCursor": 1,
            "hash_e2b21dfe": 1,
            "hash_dabbb2e7": "uin_cp_screentext_auto_main",
            "hash_f49bdf40": "localized19#hash_171d7a0b451b434d",
            "DrawByLineScreenMax": 0,
            "ShowNewLineMarker": 0,
            "RemoveCursorOnComplete": 1,
            "FlashHighlight": 0,
            "MaskText": 0,
            "DrawByLine": 1
        },
        {
            "hash_4cae1b36": 0,
            "hash_fce3a1c3": 0,
            "HideCursor": 1,
            "hash_e2b21dfe": 1,
            "hash_dabbb2e7": "uin_cp_screentext_auto_main",
            "hash_f49bdf40": "localized19#hash_171d790b451b419a",
            "DrawByLineScreenMax": 0,
            "ShowNewLineMarker": 0,
            "RemoveCursorOnComplete": 1,
            "FlashHighlight": 0,
            "MaskText": 0,
            "DrawByLine": 1
        },
        {
            "hash_4cae1b36": 0,
            "hash_fce3a1c3": 0,
            "HideCursor": 1,
            "hash_e2b21dfe": 1,
            "hash_dabbb2e7": "uin_cp_screentext_auto_main",
            "hash_f49bdf40": "localized19#hash_171d780b451b3fe7",
            "DrawByLineScreenMax": 0,
            "ShowNewLineMarker": 0,
            "RemoveCursorOnComplete": 1,
            "FlashHighlight": 0,
            "MaskText": 0,
            "DrawByLine": 1
        },
        {
            "hash_4cae1b36": 0,
            "hash_fce3a1c3": 0,
            "HideCursor": 1,
            "hash_e2b21dfe": 1,
            "hash_dabbb2e7": "uin_cp_screentext_auto_main",
            "hash_f49bdf40": "localized19#hash_171d770b451b3e34",
            "DrawByLineScreenMax": 0,
            "ShowNewLineMarker": 0,
            "RemoveCursorOnComplete": 1,
            "FlashHighlight": 0,
            "MaskText": 0,
            "DrawByLine": 1
        },
        {
            "hash_4cae1b36": 0,
            "hash_fce3a1c3": 0,
            "HideCursor": 0,
            "hash_e2b21dfe": 1,
            "hash_dabbb2e7": "uin_cp_screentext_auto_main",
            "hash_f49bdf40": "localized19#hash_171d6e0b451b2ee9",
            "DrawByLineScreenMax": 0,
            "ShowNewLineMarker": 0,
            "RemoveCursorOnComplete": 1,
            "FlashHighlight": 0,
            "MaskText": 0,
            "DrawByLine": 0
        }
    ],
    "configstringfiletype": "scriptbundle",
    "type": "computerscreencontentlists",
    "name": "cp_rus_kgb_reprogram_computer_remapping"
}