{
    "var_e1f3b51": [
        {
            "var_8bd0af73": "#bundle_reactive_2004_tr_damagesemi_fuego_mtxbundle"
        }
    ],
    "itemname": "#hash_5262dd31b8ce5b49",
    "var_e9d9a8d0": 1,
    "var_728341a": 1,
    "var_375a1747": "#hash_723cb9895d45a32c",
    "season": 2,
    "var_46300498": 1,
    "name": "callingcards_fuego_animated_mtxitem",
    "calling_card": "#hash_5262dd31b8ce5b49",
    "category": "#calling_card",
    "var_db3e02ab": 2000,
    "var_700702e5": 2000,
    "rarity": 4,
    "itemid": "22944397"
}