{
    "var_71e6f25": "#hash_5b3e84b96207ed96",
    "requestfutzsupplydrop": "#hash_599c36d917736f96",
    "laststanddown": "#hash_8e7df52619dcaed",
    "var_69ee8f4a": "#hash_1e309315a8f4f9f1",
    "requesthelicopter": "#hash_3c872660cac7f3ff",
    "revive": "#hash_54ef95c92ab6fae7",
    "requestcounteruav": "#hash_61319e3c5df3bed2",
    "threatcounteruav": "#hash_7d59263c3bfc981b",
    "requestaitank": "#hash_5e23b79de41db0f",
    "var_61f7feba": "#hash_392fad5dca76f49e",
    "var_922067c4": "scriptbundle",
    "respawned": "#hash_6b68a9374f0dfca2",
    "var_94f7b414": "#hash_717857ea47d9ed2d",
    "killenemy": "#hash_64abbc8da82c1ac4",
    "var_e765543e": "#hash_1a4583ee35103d77",
    "threatuav": "#hash_18e46157767cc1f0",
    "requestuav": "#hash_17bba148179f8373",
    "controlaitank": "#hash_4b70294db42c7917",
    "requestfutzrcbomb": "#hash_6b1027a1c4fb55b8",
    "type": "mpdialog_player",
    "requestsupplydrop": "#hash_2ed4ab6dcc91e380",
    "requestfutzultturret": "#hash_6ac3bf8ea7773e0f",
    "requestfutzplanemortar": "#hash_3ab5e53e76d7c141",
    "destroyedultturret": "#hash_1bf27088ba1811d3",
    "requestfutzstraferun": "#hash_7866f4f2232db071",
    "requeststraferun": "#hash_295c440e80e4e4ad",
    "requestplanemortar": "#hash_5fc64932e0b656dd",
    "var_d0b5ae02": "#hash_244c0e35d8558020",
    "requestdart": "#hash_429ae0168e70cfe4",
    "callinfutzremotemissile": "#hash_4900750640c85a82",
    "vmtype": "both",
    "requestoverwatchhelicopter": "#hash_301b6d973653db24",
    "requestfutzhelicopter": "#hash_19fb53609d3676bb",
    "var_93fb4152": "#hash_5cb1d70a2fbbddd6",
    "threatultturret": "#hash_521502c49bc4748",
    "threatrcbomb": "#hash_320e4409ef70d90b",
    "destroyedoverwatchhelicopter": "#hash_514a1032f84544a2",
    "destroyeduav": "#hash_350acb47497a145b",
    "name": "engineer",
    "var_6a4b9d1b": "#hash_2f3e7aa30983369f",
    "requestrcbomb": "#hash_5534968f563ad4c2",
    "var_5a7b473e": "#hash_78e201cbc10e6942",
    "var_adaebe66": "#hash_32b357efa49c39f8",
    "destroyedcounteruav": "#hash_6de6a523dc138bda",
    "requestultturret": "#hash_fd510b6ebe546b",
    "destroyedrcbomb": "#hash_36d75f5a859812ca",
    "var_75a78df2": "#hash_7bd934a7ce43300b",
    "threatoverwatchhelicopter": "#hash_e556185ce54bee3",
    "destroyedhelicopter": "#hash_599014d6ccf99b8d",
    "callinremotemissile": "#hash_5ad78b346d667dc4",
    "destroyedstraferun": "#hash_14e49ffd512a5aa7",
    "threatstraferun": "#hash_36ecd2ac528914bc",
    "threathelicopter": "#hash_f8690c5ea5a4396",
    "var_7c09c5ae": "#hash_492c31c5d681006f",
    "var_8e19817d": "#hash_623b88634792d195",
    "var_4ce86d55": "#hash_28cbd9d5dcf349e3",
    "var_32dba6a": "#hash_7575ba5828d388c0",
    "reload": "#hash_272c73a181c5cd64",
    "destroyeddart": "#hash_5d70d87643cdca3c",
    "requestfutzdart": "#hash_74c081c70dcdafe2",
    "destroyedaitank": "#hash_3004841144bf863d",
    "threataitank": "#hash_21d8c56a4f4133c6",
    "requestfutzcounteruav": "#hash_3fcde6946d177b68",
    "requestfutzuav": "#hash_7d55230b55cfece7",
    "takingfire": "#hash_629bb9c8ec506456",
    "requestfutzaitank": "#hash_351fb9c137f631ab",
    "requestoverwatchfutzhelicopter": "#hash_30485d86eb259e22",
    "var_e03ac407": "#hash_1377da8f3c181972",
    "threatsupplydrop": "#hash_49b9512360bd2d"
}