{
    "objects": [
        {
            "shots": [
                {
                    "entry": [
                        {
                            "anim": "#hash_29faa794b820fe7a",
                            "var_71bac06": "anim"
                        }
                    ],
                    "cleanupdelete": 1,
                    "name": "shot 1"
                },
                {
                    "entry": [
                        {
                            "anim": "#hash_1a2d19140acaf911",
                            "var_71bac06": "anim"
                        }
                    ],
                    "cleanupdelete": 1,
                    "name": "shot 2"
                },
                {
                    "entry": [
                        {
                            "anim": "#hash_4cf947182dd5e870",
                            "var_71bac06": "anim"
                        }
                    ],
                    "cleanupdelete": 1,
                    "name": "shot 3"
                }
            ],
            "model": "#hash_5958f8fe5e577540",
            "type": "prop",
            "var_db255011": 1,
            "name": "bomb"
        }
    ],
    "scenetype": "scene",
    "var_922067c4": "scriptbundle",
    "devstate": "placeholder",
    "type": "scene",
    "name": "p9_fxanim_mp_napalm_strike_spin",
    "dontsync": 1,
    "team": "any"
}