{
    "entitlementlist": [
        {
            "var_386af035": "#firstparty_bundle_3307_code_medic_pack_ms_mtxentitlement"
        }
    ],
    "itemname": "#hash_ab4776bb366bc0",
    "var_e9d9a8d0": 1,
    "var_be574bd8": "#hash_ab4776bb366bc0",
    "var_728341a": 1,
    "var_375a1747": "#hash_723cb9895d45a32c",
    "season": 3,
    "var_46300498": 1,
    "bodytype": "#hash_781cfcdc0650d9a3",
    "name": "po_c_t9_usa_pl_cia_macv_code_ms_mtxitem",
    "category": "#character_outfit",
    "var_db3e02ab": 2000,
    "var_700702e5": 2000,
    "rarity": 3,
    "itemid": "26111804",
    "outfit": "#hash_ab4776bb366bc0"
}