{
    "#hash_50c23eb3": [
        {
            "track": "scriptbundle#battletrack_waw_blackcats"
        },
        {
            "track": "scriptbundle#battletrack_waw_dogfire"
        },
        {
            "track": "scriptbundle#battletrack_waw_hellsgate"
        },
        {
            "track": "scriptbundle#battletrack_waw_wildcard"
        }
    ],
    "name": "battletrack_pack_season5_wawmixtape",
    "hash_6855e4be": "#battletrack_pack_season5_wawmixtape_mtxitem",
    "title": "localized18#hash_16b44a73fa9a3d6c",
    "hash_9bf5cf77": 0
}