{
    "bundlelist": [
        {
            "hash_8bd0af73": "#paragon_mp_t6_06_bundle_mtxbundle"
        }
    ],
    "itemname": "#hash_c2a64c3ac025af9",
    "hash_e9d9a8d0": 1,
    "hash_4f3108ff": 0,
    "hash_841f8748": 0,
    "hash_5c813d34": 0,
    "hash_728341a": 1,
    "quantity": 0,
    "hash_375a1747": "image#ui_icon_mtx_billboards_placeholder",
    "release": 0,
    "season": 1,
    "hash_46300498": 1,
    "hash_8ee7db29": 0,
    "hash_7f1fd6e2": 0,
    "hash_b6d84534": 0,
    "name": "paragon_mp_t6_06_mtxitem",
    "prestige_icon": "#hash_c2a64c3ac025af9",
    "hash_f3d04949": 0,
    "category": "#prestige_icon",
    "hash_db3e02ab": 2000,
    "hash_700702e5": 2000,
    "rarity": "enum:9",
    "hash_84dc7961": 0,
    "itemid": "22218566"
}